alt_event_system/__init__.py
alt_event_system/constants.py
alt_event_system/core.py
alt_event_system/exceptions.py
alt_event_system/py.typed
alt_event_system-0.1.0.dist-info/licenses/LICENSE
alt_event_system-0.1.0.dist-info/METADATA
alt_event_system-0.1.0.dist-info/WHEEL
alt_event_system-0.1.0.dist-info/top_level.txt
alt_event_system-0.1.0.dist-info/RECORD
