Metadata-Version: 2.4
Name: ALT-event-system
Version: 0.1.0
Summary: A lightweight publish-subscribe event system for Python
Author-email: Avi Layani <avilayani@gmail.com>
License: MIT
Project-URL: Homepage, https://github.com/Avilir/ALT-event-system
Project-URL: Bug Reports, https://github.com/Avilir/ALT-event-system/issues
Project-URL: Source, https://github.com/Avilir/ALT-event-system
Keywords: events,event-driven,pubsub,publish-subscribe,event-bus,observer,messaging
Classifier: Development Status :: 4 - Beta
Classifier: Intended Audience :: Developers
Classifier: License :: OSI Approved :: MIT License
Classifier: Operating System :: OS Independent
Classifier: Programming Language :: Python :: 3
Classifier: Programming Language :: Python :: 3.8
Classifier: Programming Language :: Python :: 3.9
Classifier: Programming Language :: Python :: 3.10
Classifier: Programming Language :: Python :: 3.11
Classifier: Programming Language :: Python :: 3.12
Classifier: Topic :: Software Development :: Libraries :: Python Modules
Classifier: Topic :: Software Development :: Libraries :: Application Frameworks
Classifier: Typing :: Typed
Requires-Python: >=3.8
License-File: LICENSE
Provides-Extra: dev
Requires-Dist: pytest>=6.0; extra == "dev"
Requires-Dist: pytest-cov>=2.10; extra == "dev"
Requires-Dist: mypy>=0.800; extra == "dev"
Requires-Dist: ruff>=0.1.0; extra == "dev"
Requires-Dist: black>=22.0; extra == "dev"
Requires-Dist: pre-commit>=2.0; extra == "dev"
Dynamic: license-file
